mqtt_ingestor/__init__.py
mqtt_ingestor/__main__.py
mqtt_ingestor/api.py
mqtt_ingestor/filter.py
mqtt_ingestor/logger.py
mqtt_ingestor/model.py
mqtt_ingestor/mqtt.py
mqtt_ingestor/filters/__init__.py
mqtt_ingestor/filters/chain2.py
mqtt_ingestor/storage/__init__.py
mqtt_ingestor/storage/base.py
mqtt_ingestor/storage/mongodb.py
mqtt_ingestor/storage/postgres.py
mqtt_ingestor/storage/sqlalchemy.py
mqtt_ingestor-1.5.0.dist-info/licenses/LICENSE
mqtt_ingestor-1.5.0.dist-info/METADATA
mqtt_ingestor-1.5.0.dist-info/WHEEL
mqtt_ingestor-1.5.0.dist-info/entry_points.txt
mqtt_ingestor-1.5.0.dist-info/top_level.txt
mqtt_ingestor-1.5.0.dist-info/RECORD
