Metadata-Version: 2.4
Name: mqtt-ingestor
Version: 1.5.0
Summary: Add your description here
Requires-Python: >=3.13
License-File: LICENSE
Requires-Dist: paho-mqtt>=2.1.0
Requires-Dist: psycopg2-binary>=2.9.11
Requires-Dist: pymongo>=4.15.3
Requires-Dist: python-dotenv>=1.1.1
Requires-Dist: sqlalchemy>=2.0.44
Dynamic: license-file
